embers/.DS_Store
embers/__init__.py
embers/__pycache__/__init__.cpython-38.pyc
embers/kindle/__init__.py
embers/kindle/align_batch.py
embers/kindle/align_single.py
embers/kindle/colormaps.py
embers/kindle/compare_beams.py
embers/kindle/download_tle.py
embers/kindle/ephem_batch.py
embers/kindle/ephem_chrono.py
embers/kindle/ephem_single.py
embers/kindle/mwa_dipoles.py
embers/kindle/mwa_fee.py
embers/kindle/mwa_pointings.py
embers/kindle/null_test.py
embers/kindle/ref_models.py
embers/kindle/rfe_calibration.py
embers/kindle/sat_channels.py
embers/kindle/tile_maps.py
embers/kindle/waterfall_batch.py
embers/kindle/waterfall_single.py
embers/kindle/__pycache__/__init__.cpython-38.pyc
embers/kindle/__pycache__/align_batch.cpython-38.pyc
embers/kindle/__pycache__/align_single.cpython-38.pyc
embers/kindle/__pycache__/colormaps.cpython-38.pyc
embers/kindle/__pycache__/compare_beams.cpython-38.pyc
embers/kindle/__pycache__/download_tle.cpython-38.pyc
embers/kindle/__pycache__/ephem_batch.cpython-38.pyc
embers/kindle/__pycache__/ephem_chrono.cpython-38.pyc
embers/kindle/__pycache__/ephem_single.cpython-38.pyc
embers/kindle/__pycache__/mwa_dipoles.cpython-38.pyc
embers/kindle/__pycache__/mwa_fee.cpython-38.pyc
embers/kindle/__pycache__/mwa_pointings.cpython-38.pyc
embers/kindle/__pycache__/null_test.cpython-38.pyc
embers/kindle/__pycache__/ref_models.cpython-38.pyc
embers/kindle/__pycache__/rfe_calibration.cpython-38.pyc
embers/kindle/__pycache__/sat_channels.cpython-38.pyc
embers/kindle/__pycache__/tile_maps.cpython-38.pyc
embers/kindle/__pycache__/waterfall_batch.cpython-38.pyc
embers/kindle/__pycache__/waterfall_single.cpython-38.pyc
embers/kindle/data/TLE/25417.txt
embers/kindle/data/ref_models/MWA_reference_tile_FarField_XX.ffe
embers/kindle/data/ref_models/MWA_reference_tile_FarField_YY.ffe
embers/kindle/data/rf_data/S06XX/2019-10-01/S06XX_2019-10-01-14:30.txt
embers/kindle/data/rf_data/S06XX/2019-10-10/S06XX_2019-10-10-02:30.txt
embers-1.0.0.dist-info/LICENSE
embers-1.0.0.dist-info/METADATA
embers-1.0.0.dist-info/WHEEL
embers-1.0.0.dist-info/entry_points.txt
embers-1.0.0.dist-info/top_level.txt
embers-1.0.0.dist-info/RECORD
